[
  {
    "config": {
      "address": "mail.agenturserver.de",
      "type": "host",
      "port": "143",
      "timeout": 5
    },
    "status": {
      "isUp": true,
      "lastCheck": 1753877363,
      "lastResultDuration": 329
    },
    "stats": {
      "allTime": {
        "total": 1126,
        "successful": 1126,
        "uptime": 100
      },
      "30d": {
        "total": 1126,
        "successful": 1126,
        "uptime": 100,
        "lastReset": 1753255731
      },
      "365d": {
        "total": 1126,
        "successful": 1126,
        "uptime": 100,
        "lastReset": 1753255731
      }
    }
  },
  {
    "config": {
      "address": "mail.agenturserver.de",
      "type": "host",
      "port": "993",
      "timeout": 5
    },
    "status": {
      "isUp": true,
      "lastCheck": 1753877364,
      "lastResultDuration": 332
    },
    "stats": {
      "allTime": {
        "total": 1125,
        "successful": 1125,
        "uptime": 100
      },
      "30d": {
        "total": 1125,
        "successful": 1125,
        "uptime": 100,
        "lastReset": 1753255731
      },
      "365d": {
        "total": 1125,
        "successful": 1125,
        "uptime": 100,
        "lastReset": 1753255731
      }
    }
  },
  {
    "config": {
      "address": "mail.agenturserver.de",
      "type": "host",
      "port": "110",
      "timeout": 5
    },
    "status": {
      "isUp": true,
      "lastCheck": 1753877364,
      "lastResultDuration": 316
    },
    "stats": {
      "allTime": {
        "total": 1125,
        "successful": 1125,
        "uptime": 100
      },
      "30d": {
        "total": 1125,
        "successful": 1125,
        "uptime": 100,
        "lastReset": 1753255731
      },
      "365d": {
        "total": 1125,
        "successful": 1125,
        "uptime": 100,
        "lastReset": 1753255731
      }
    }
  },
  {
    "config": {
      "address": "mail.agenturserver.de",
      "type": "host",
      "port": "995",
      "timeout": 5
    },
    "status": {
      "isUp": true,
      "lastCheck": 1753877364,
      "lastResultDuration": 316
    },
    "stats": {
      "allTime": {
        "total": 1125,
        "successful": 1125,
        "uptime": 100
      },
      "30d": {
        "total": 1125,
        "successful": 1125,
        "uptime": 100,
        "lastReset": 1753255731
      },
      "365d": {
        "total": 1125,
        "successful": 1125,
        "uptime": 100,
        "lastReset": 1753255731
      }
    }
  },
  {
    "config": {
      "address": "mail.agenturserver.de",
      "type": "host",
      "port": "465",
      "timeout": 5
    },
    "status": {
      "isUp": true,
      "lastCheck": 1753877365,
      "lastResultDuration": 321
    },
    "stats": {
      "allTime": {
        "total": 1125,
        "successful": 1125,
        "uptime": 100
      },
      "30d": {
        "total": 1125,
        "successful": 1125,
        "uptime": 100,
        "lastReset": 1753255731
      },
      "365d": {
        "total": 1125,
        "successful": 1125,
        "uptime": 100,
        "lastReset": 1753255731
      }
    }
  },
  {
    "config": {
      "address": "mail.agenturserver.de",
      "type": "host",
      "port": "587",
      "timeout": 5
    },
    "status": {
      "isUp": true,
      "lastCheck": 1753877365,
      "lastResultDuration": 324
    },
    "stats": {
      "allTime": {
        "total": 1125,
        "successful": 1125,
        "uptime": 100
      },
      "30d": {
        "total": 1125,
        "successful": 1125,
        "uptime": 100,
        "lastReset": 1753255731
      },
      "365d": {
        "total": 1125,
        "successful": 1125,
        "uptime": 100,
        "lastReset": 1753255731
      }
    }
  },
  {
    "config": {
      "address": "185.237.66.112",
      "type": "host",
      "port": "80",
      "timeout": 5
    },
    "status": {
      "isUp": true,
      "lastCheck": 1753877365,
      "lastResultDuration": 158
    },
    "stats": {
      "allTime": {
        "total": 1125,
        "successful": 1125,
        "uptime": 100
      },
      "30d": {
        "total": 1125,
        "successful": 1125,
        "uptime": 100,
        "lastReset": 1753255731
      },
      "365d": {
        "total": 1125,
        "successful": 1125,
        "uptime": 100,
        "lastReset": 1753255731
      }
    }
  },
  {
    "config": {
      "address": "157.97.45.248",
      "type": "host",
      "port": "80",
      "timeout": 5
    },
    "status": {
      "isUp": true,
      "lastCheck": 1753877365,
      "lastResultDuration": 162
    },
    "stats": {
      "allTime": {
        "total": 1125,
        "successful": 1125,
        "uptime": 100
      },
      "30d": {
        "total": 1125,
        "successful": 1125,
        "uptime": 100,
        "lastReset": 1753255731
      },
      "365d": {
        "total": 1125,
        "successful": 1125,
        "uptime": 100,
        "lastReset": 1753255731
      }
    }
  },
  {
    "config": {
      "address": "85.13.152.121",
      "type": "host",
      "port": "80",
      "timeout": 5
    },
    "status": {
      "isUp": true,
      "lastCheck": 1753877366,
      "lastResultDuration": 163
    },
    "stats": {
      "allTime": {
        "total": 1125,
        "successful": 1125,
        "uptime": 100
      },
      "30d": {
        "total": 1125,
        "successful": 1125,
        "uptime": 100,
        "lastReset": 1753255731
      },
      "365d": {
        "total": 1125,
        "successful": 1125,
        "uptime": 100,
        "lastReset": 1753255731
      }
    }
  },
  {
    "config": {
      "address": "https://login.pixelsaft.de",
      "type": "url",
      "port": null,
      "timeout": 5
    },
    "status": {
      "isUp": true,
      "lastCheck": 1753877367,
      "lastResultDuration": 1732
    },
    "stats": {
      "allTime": {
        "total": 1125,
        "successful": 1124,
        "uptime": 99.91
      },
      "30d": {
        "total": 1125,
        "successful": 1124,
        "uptime": 99.91,
        "lastReset": 1753255731
      },
      "365d": {
        "total": 1125,
        "successful": 1124,
        "uptime": 99.91,
        "lastReset": 1753255731
      }
    }
  },
  {
    "config": {
      "address": "ns1.pixelsaft.de",
      "type": "host",
      "port": "53",
      "timeout": 5
    },
    "status": {
      "isUp": true,
      "lastCheck": 1753877368,
      "lastResultDuration": 862
    },
    "stats": {
      "allTime": {
        "total": 1125,
        "successful": 1124,
        "uptime": 99.91
      },
      "30d": {
        "total": 1125,
        "successful": 1124,
        "uptime": 99.91,
        "lastReset": 1753255731
      },
      "365d": {
        "total": 1125,
        "successful": 1124,
        "uptime": 99.91,
        "lastReset": 1753255731
      }
    }
  },
  {
    "config": {
      "address": "ns2.pixelsaft.de",
      "type": "host",
      "port": "53",
      "timeout": 5
    },
    "status": {
      "isUp": true,
      "lastCheck": 1753877368,
      "lastResultDuration": 221
    },
    "stats": {
      "allTime": {
        "total": 1125,
        "successful": 1125,
        "uptime": 100
      },
      "30d": {
        "total": 1125,
        "successful": 1125,
        "uptime": 100,
        "lastReset": 1753255731
      },
      "365d": {
        "total": 1125,
        "successful": 1125,
        "uptime": 100,
        "lastReset": 1753255731
      }
    }
  },
  {
    "config": {
      "address": "ns3.pixelsaft.de",
      "type": "host",
      "port": "53",
      "timeout": 5
    },
    "status": {
      "isUp": true,
      "lastCheck": 1753877369,
      "lastResultDuration": 160
    },
    "stats": {
      "allTime": {
        "total": 1125,
        "successful": 1125,
        "uptime": 100
      },
      "30d": {
        "total": 1125,
        "successful": 1125,
        "uptime": 100,
        "lastReset": 1753255731
      },
      "365d": {
        "total": 1125,
        "successful": 1125,
        "uptime": 100,
        "lastReset": 1753255731
      }
    }
  },
  {
    "config": {
      "address": "ns4.pixelsaft.de",
      "type": "host",
      "port": "53",
      "timeout": 5
    },
    "status": {
      "isUp": true,
      "lastCheck": 1753877369,
      "lastResultDuration": 901
    },
    "stats": {
      "allTime": {
        "total": 1125,
        "successful": 1125,
        "uptime": 100
      },
      "30d": {
        "total": 1125,
        "successful": 1125,
        "uptime": 100,
        "lastReset": 1753255731
      },
      "365d": {
        "total": 1125,
        "successful": 1125,
        "uptime": 100,
        "lastReset": 1753255731
      }
    }
  }
]