[
  {
    "config": {
      "address": "mail.agenturserver.de",
      "type": "host",
      "port": "143",
      "timeout": 5
    },
    "status": {
      "isUp": true,
      "lastCheck": 1760161661,
      "lastResultDuration": 208
    },
    "stats": {
      "allTime": {
        "total": 7365,
        "successful": 7352,
        "uptime": 99.82
      },
      "30d": {
        "total": 1737,
        "successful": 1737,
        "uptime": 100,
        "lastReset": 1758440893
      },
      "365d": {
        "total": 7365,
        "successful": 7352,
        "uptime": 99.82,
        "lastReset": 1753255731
      }
    }
  },
  {
    "config": {
      "address": "mail.agenturserver.de",
      "type": "host",
      "port": "993",
      "timeout": 5
    },
    "status": {
      "isUp": true,
      "lastCheck": 1760161662,
      "lastResultDuration": 196
    },
    "stats": {
      "allTime": {
        "total": 7364,
        "successful": 7358,
        "uptime": 99.92
      },
      "30d": {
        "total": 1737,
        "successful": 1737,
        "uptime": 100,
        "lastReset": 1758440894
      },
      "365d": {
        "total": 7364,
        "successful": 7358,
        "uptime": 99.92,
        "lastReset": 1753255731
      }
    }
  },
  {
    "config": {
      "address": "mail.agenturserver.de",
      "type": "host",
      "port": "110",
      "timeout": 5
    },
    "status": {
      "isUp": true,
      "lastCheck": 1760161662,
      "lastResultDuration": 99
    },
    "stats": {
      "allTime": {
        "total": 7364,
        "successful": 7360,
        "uptime": 99.95
      },
      "30d": {
        "total": 1737,
        "successful": 1737,
        "uptime": 100,
        "lastReset": 1758440894
      },
      "365d": {
        "total": 7364,
        "successful": 7360,
        "uptime": 99.95,
        "lastReset": 1753255731
      }
    }
  },
  {
    "config": {
      "address": "mail.agenturserver.de",
      "type": "host",
      "port": "995",
      "timeout": 5
    },
    "status": {
      "isUp": true,
      "lastCheck": 1760161662,
      "lastResultDuration": 196
    },
    "stats": {
      "allTime": {
        "total": 7364,
        "successful": 7359,
        "uptime": 99.93
      },
      "30d": {
        "total": 1737,
        "successful": 1737,
        "uptime": 100,
        "lastReset": 1758440894
      },
      "365d": {
        "total": 7364,
        "successful": 7359,
        "uptime": 99.93,
        "lastReset": 1753255731
      }
    }
  },
  {
    "config": {
      "address": "mail.agenturserver.de",
      "type": "host",
      "port": "465",
      "timeout": 5
    },
    "status": {
      "isUp": true,
      "lastCheck": 1760161662,
      "lastResultDuration": 196
    },
    "stats": {
      "allTime": {
        "total": 7364,
        "successful": 7357,
        "uptime": 99.9
      },
      "30d": {
        "total": 1737,
        "successful": 1737,
        "uptime": 100,
        "lastReset": 1758440894
      },
      "365d": {
        "total": 7364,
        "successful": 7357,
        "uptime": 99.9,
        "lastReset": 1753255731
      }
    }
  },
  {
    "config": {
      "address": "mail.agenturserver.de",
      "type": "host",
      "port": "587",
      "timeout": 5
    },
    "status": {
      "isUp": true,
      "lastCheck": 1760161662,
      "lastResultDuration": 195
    },
    "stats": {
      "allTime": {
        "total": 7364,
        "successful": 7362,
        "uptime": 99.97
      },
      "30d": {
        "total": 1737,
        "successful": 1736,
        "uptime": 99.94,
        "lastReset": 1758440895
      },
      "365d": {
        "total": 7364,
        "successful": 7362,
        "uptime": 99.97,
        "lastReset": 1753255731
      }
    }
  },
  {
    "config": {
      "address": "185.237.66.112",
      "type": "host",
      "port": "80",
      "timeout": 5
    },
    "status": {
      "isUp": true,
      "lastCheck": 1760161662,
      "lastResultDuration": 98
    },
    "stats": {
      "allTime": {
        "total": 7364,
        "successful": 7363,
        "uptime": 99.99
      },
      "30d": {
        "total": 1737,
        "successful": 1737,
        "uptime": 100,
        "lastReset": 1758440895
      },
      "365d": {
        "total": 7364,
        "successful": 7363,
        "uptime": 99.99,
        "lastReset": 1753255731
      }
    }
  },
  {
    "config": {
      "address": "157.97.45.248",
      "type": "host",
      "port": "80",
      "timeout": 5
    },
    "status": {
      "isUp": true,
      "lastCheck": 1760161662,
      "lastResultDuration": 97
    },
    "stats": {
      "allTime": {
        "total": 7364,
        "successful": 7361,
        "uptime": 99.96
      },
      "30d": {
        "total": 1737,
        "successful": 1736,
        "uptime": 99.94,
        "lastReset": 1758440895
      },
      "365d": {
        "total": 7364,
        "successful": 7361,
        "uptime": 99.96,
        "lastReset": 1753255731
      }
    }
  },
  {
    "config": {
      "address": "85.13.152.121",
      "type": "host",
      "port": "80",
      "timeout": 5
    },
    "status": {
      "isUp": true,
      "lastCheck": 1760161663,
      "lastResultDuration": 111
    },
    "stats": {
      "allTime": {
        "total": 7364,
        "successful": 7358,
        "uptime": 99.92
      },
      "30d": {
        "total": 1737,
        "successful": 1735,
        "uptime": 99.88,
        "lastReset": 1758440895
      },
      "365d": {
        "total": 7364,
        "successful": 7358,
        "uptime": 99.92,
        "lastReset": 1753255731
      }
    }
  },
  {
    "config": {
      "address": "https://login.pixelsaft.de",
      "type": "url",
      "port": null,
      "timeout": 5
    },
    "status": {
      "isUp": true,
      "lastCheck": 1760161664,
      "lastResultDuration": 1137
    },
    "stats": {
      "allTime": {
        "total": 7364,
        "successful": 7346,
        "uptime": 99.76
      },
      "30d": {
        "total": 1737,
        "successful": 1737,
        "uptime": 100,
        "lastReset": 1758440897
      },
      "365d": {
        "total": 7364,
        "successful": 7346,
        "uptime": 99.76,
        "lastReset": 1753255731
      }
    }
  },
  {
    "config": {
      "address": "ns1.pixelsaft.de",
      "type": "host",
      "port": "53",
      "timeout": 5
    },
    "status": {
      "isUp": true,
      "lastCheck": 1760161664,
      "lastResultDuration": 505
    },
    "stats": {
      "allTime": {
        "total": 7364,
        "successful": 7361,
        "uptime": 99.96
      },
      "30d": {
        "total": 1737,
        "successful": 1735,
        "uptime": 99.88,
        "lastReset": 1758440897
      },
      "365d": {
        "total": 7364,
        "successful": 7361,
        "uptime": 99.96,
        "lastReset": 1753255731
      }
    }
  },
  {
    "config": {
      "address": "ns2.pixelsaft.de",
      "type": "host",
      "port": "53",
      "timeout": 5
    },
    "status": {
      "isUp": true,
      "lastCheck": 1760161665,
      "lastResultDuration": 309
    },
    "stats": {
      "allTime": {
        "total": 7364,
        "successful": 7359,
        "uptime": 99.93
      },
      "30d": {
        "total": 1737,
        "successful": 1735,
        "uptime": 99.88,
        "lastReset": 1758440897
      },
      "365d": {
        "total": 7364,
        "successful": 7359,
        "uptime": 99.93,
        "lastReset": 1753255731
      }
    }
  },
  {
    "config": {
      "address": "ns3.pixelsaft.de",
      "type": "host",
      "port": "53",
      "timeout": 5
    },
    "status": {
      "isUp": true,
      "lastCheck": 1760161665,
      "lastResultDuration": 179
    },
    "stats": {
      "allTime": {
        "total": 7364,
        "successful": 7360,
        "uptime": 99.95
      },
      "30d": {
        "total": 1737,
        "successful": 1737,
        "uptime": 100,
        "lastReset": 1758440897
      },
      "365d": {
        "total": 7364,
        "successful": 7360,
        "uptime": 99.95,
        "lastReset": 1753255731
      }
    }
  },
  {
    "config": {
      "address": "ns4.pixelsaft.de",
      "type": "host",
      "port": "53",
      "timeout": 5
    },
    "status": {
      "isUp": true,
      "lastCheck": 1760161665,
      "lastResultDuration": 40
    },
    "stats": {
      "allTime": {
        "total": 7364,
        "successful": 7359,
        "uptime": 99.93
      },
      "30d": {
        "total": 1737,
        "successful": 1737,
        "uptime": 100,
        "lastReset": 1758440898
      },
      "365d": {
        "total": 7364,
        "successful": 7359,
        "uptime": 99.93,
        "lastReset": 1753255731
      }
    }
  }
]