[
  {
    "config": {
      "address": "mail.agenturserver.de",
      "type": "host",
      "port": "143",
      "timeout": 5
    },
    "status": {
      "isUp": true,
      "lastCheck": 1758016100,
      "lastResultDuration": 215
    },
    "stats": {
      "allTime": {
        "total": 5199,
        "successful": 5191,
        "uptime": 99.85
      },
      "30d": {
        "total": 2187,
        "successful": 2180,
        "uptime": 99.68,
        "lastReset": 1755848046
      },
      "365d": {
        "total": 5199,
        "successful": 5191,
        "uptime": 99.85,
        "lastReset": 1753255731
      }
    }
  },
  {
    "config": {
      "address": "mail.agenturserver.de",
      "type": "host",
      "port": "993",
      "timeout": 5
    },
    "status": {
      "isUp": true,
      "lastCheck": 1758016101,
      "lastResultDuration": 199
    },
    "stats": {
      "allTime": {
        "total": 5198,
        "successful": 5193,
        "uptime": 99.9
      },
      "30d": {
        "total": 2187,
        "successful": 2186,
        "uptime": 99.95,
        "lastReset": 1755848047
      },
      "365d": {
        "total": 5198,
        "successful": 5193,
        "uptime": 99.9,
        "lastReset": 1753255731
      }
    }
  },
  {
    "config": {
      "address": "mail.agenturserver.de",
      "type": "host",
      "port": "110",
      "timeout": 5
    },
    "status": {
      "isUp": true,
      "lastCheck": 1758016101,
      "lastResultDuration": 198
    },
    "stats": {
      "allTime": {
        "total": 5198,
        "successful": 5196,
        "uptime": 99.96
      },
      "30d": {
        "total": 2187,
        "successful": 2186,
        "uptime": 99.95,
        "lastReset": 1755848047
      },
      "365d": {
        "total": 5198,
        "successful": 5196,
        "uptime": 99.96,
        "lastReset": 1753255731
      }
    }
  },
  {
    "config": {
      "address": "mail.agenturserver.de",
      "type": "host",
      "port": "995",
      "timeout": 5
    },
    "status": {
      "isUp": true,
      "lastCheck": 1758016101,
      "lastResultDuration": 288
    },
    "stats": {
      "allTime": {
        "total": 5198,
        "successful": 5194,
        "uptime": 99.92
      },
      "30d": {
        "total": 2187,
        "successful": 2185,
        "uptime": 99.91,
        "lastReset": 1755848047
      },
      "365d": {
        "total": 5198,
        "successful": 5194,
        "uptime": 99.92,
        "lastReset": 1753255731
      }
    }
  },
  {
    "config": {
      "address": "mail.agenturserver.de",
      "type": "host",
      "port": "465",
      "timeout": 5
    },
    "status": {
      "isUp": true,
      "lastCheck": 1758016101,
      "lastResultDuration": 290
    },
    "stats": {
      "allTime": {
        "total": 5198,
        "successful": 5192,
        "uptime": 99.88
      },
      "30d": {
        "total": 2187,
        "successful": 2185,
        "uptime": 99.91,
        "lastReset": 1755848047
      },
      "365d": {
        "total": 5198,
        "successful": 5192,
        "uptime": 99.88,
        "lastReset": 1753255731
      }
    }
  },
  {
    "config": {
      "address": "mail.agenturserver.de",
      "type": "host",
      "port": "587",
      "timeout": 5
    },
    "status": {
      "isUp": true,
      "lastCheck": 1758016102,
      "lastResultDuration": 198
    },
    "stats": {
      "allTime": {
        "total": 5198,
        "successful": 5197,
        "uptime": 99.98
      },
      "30d": {
        "total": 2187,
        "successful": 2187,
        "uptime": 100,
        "lastReset": 1755848048
      },
      "365d": {
        "total": 5198,
        "successful": 5197,
        "uptime": 99.98,
        "lastReset": 1753255731
      }
    }
  },
  {
    "config": {
      "address": "185.237.66.112",
      "type": "host",
      "port": "80",
      "timeout": 5
    },
    "status": {
      "isUp": true,
      "lastCheck": 1758016102,
      "lastResultDuration": 99
    },
    "stats": {
      "allTime": {
        "total": 5198,
        "successful": 5197,
        "uptime": 99.98
      },
      "30d": {
        "total": 2187,
        "successful": 2186,
        "uptime": 99.95,
        "lastReset": 1755848048
      },
      "365d": {
        "total": 5198,
        "successful": 5197,
        "uptime": 99.98,
        "lastReset": 1753255731
      }
    }
  },
  {
    "config": {
      "address": "157.97.45.248",
      "type": "host",
      "port": "80",
      "timeout": 5
    },
    "status": {
      "isUp": true,
      "lastCheck": 1758016102,
      "lastResultDuration": 102
    },
    "stats": {
      "allTime": {
        "total": 5198,
        "successful": 5196,
        "uptime": 99.96
      },
      "30d": {
        "total": 2187,
        "successful": 2185,
        "uptime": 99.91,
        "lastReset": 1755848048
      },
      "365d": {
        "total": 5198,
        "successful": 5196,
        "uptime": 99.96,
        "lastReset": 1753255731
      }
    }
  },
  {
    "config": {
      "address": "85.13.152.121",
      "type": "host",
      "port": "80",
      "timeout": 5
    },
    "status": {
      "isUp": true,
      "lastCheck": 1758016102,
      "lastResultDuration": 109
    },
    "stats": {
      "allTime": {
        "total": 5198,
        "successful": 5194,
        "uptime": 99.92
      },
      "30d": {
        "total": 2187,
        "successful": 2185,
        "uptime": 99.91,
        "lastReset": 1755848048
      },
      "365d": {
        "total": 5198,
        "successful": 5194,
        "uptime": 99.92,
        "lastReset": 1753255731
      }
    }
  },
  {
    "config": {
      "address": "https://login.pixelsaft.de",
      "type": "url",
      "port": null,
      "timeout": 5
    },
    "status": {
      "isUp": true,
      "lastCheck": 1758016103,
      "lastResultDuration": 767
    },
    "stats": {
      "allTime": {
        "total": 5198,
        "successful": 5183,
        "uptime": 99.71
      },
      "30d": {
        "total": 2187,
        "successful": 2178,
        "uptime": 99.59,
        "lastReset": 1755848049
      },
      "365d": {
        "total": 5198,
        "successful": 5183,
        "uptime": 99.71,
        "lastReset": 1753255731
      }
    }
  },
  {
    "config": {
      "address": "ns1.pixelsaft.de",
      "type": "host",
      "port": "53",
      "timeout": 5
    },
    "status": {
      "isUp": true,
      "lastCheck": 1758016103,
      "lastResultDuration": 183
    },
    "stats": {
      "allTime": {
        "total": 5198,
        "successful": 5197,
        "uptime": 99.98
      },
      "30d": {
        "total": 2187,
        "successful": 2187,
        "uptime": 100,
        "lastReset": 1755848050
      },
      "365d": {
        "total": 5198,
        "successful": 5197,
        "uptime": 99.98,
        "lastReset": 1753255731
      }
    }
  },
  {
    "config": {
      "address": "ns2.pixelsaft.de",
      "type": "host",
      "port": "53",
      "timeout": 5
    },
    "status": {
      "isUp": true,
      "lastCheck": 1758016103,
      "lastResultDuration": 194
    },
    "stats": {
      "allTime": {
        "total": 5198,
        "successful": 5196,
        "uptime": 99.96
      },
      "30d": {
        "total": 2187,
        "successful": 2187,
        "uptime": 100,
        "lastReset": 1755848051
      },
      "365d": {
        "total": 5198,
        "successful": 5196,
        "uptime": 99.96,
        "lastReset": 1753255731
      }
    }
  },
  {
    "config": {
      "address": "ns3.pixelsaft.de",
      "type": "host",
      "port": "53",
      "timeout": 5
    },
    "status": {
      "isUp": true,
      "lastCheck": 1758016103,
      "lastResultDuration": 177
    },
    "stats": {
      "allTime": {
        "total": 5198,
        "successful": 5194,
        "uptime": 99.92
      },
      "30d": {
        "total": 2187,
        "successful": 2187,
        "uptime": 100,
        "lastReset": 1755848052
      },
      "365d": {
        "total": 5198,
        "successful": 5194,
        "uptime": 99.92,
        "lastReset": 1753255731
      }
    }
  },
  {
    "config": {
      "address": "ns4.pixelsaft.de",
      "type": "host",
      "port": "53",
      "timeout": 5
    },
    "status": {
      "isUp": true,
      "lastCheck": 1758016103,
      "lastResultDuration": 35
    },
    "stats": {
      "allTime": {
        "total": 5198,
        "successful": 5194,
        "uptime": 99.92
      },
      "30d": {
        "total": 2187,
        "successful": 2184,
        "uptime": 99.86,
        "lastReset": 1755848052
      },
      "365d": {
        "total": 5198,
        "successful": 5194,
        "uptime": 99.92,
        "lastReset": 1753255731
      }
    }
  }
]