[
  {
    "config": {
      "address": "mail.agenturserver.de",
      "type": "host",
      "port": "143",
      "timeout": 5
    },
    "status": {
      "isUp": true,
      "lastCheck": 1757054439,
      "lastResultDuration": 901
    },
    "stats": {
      "allTime": {
        "total": 4224,
        "successful": 4218,
        "uptime": 99.86
      },
      "30d": {
        "total": 1212,
        "successful": 1207,
        "uptime": 99.59,
        "lastReset": 1755848046
      },
      "365d": {
        "total": 4224,
        "successful": 4218,
        "uptime": 99.86,
        "lastReset": 1753255731
      }
    }
  },
  {
    "config": {
      "address": "mail.agenturserver.de",
      "type": "host",
      "port": "993",
      "timeout": 5
    },
    "status": {
      "isUp": true,
      "lastCheck": 1757054439,
      "lastResultDuration": 227
    },
    "stats": {
      "allTime": {
        "total": 4223,
        "successful": 4219,
        "uptime": 99.91
      },
      "30d": {
        "total": 1212,
        "successful": 1212,
        "uptime": 100,
        "lastReset": 1755848047
      },
      "365d": {
        "total": 4223,
        "successful": 4219,
        "uptime": 99.91,
        "lastReset": 1753255731
      }
    }
  },
  {
    "config": {
      "address": "mail.agenturserver.de",
      "type": "host",
      "port": "110",
      "timeout": 5
    },
    "status": {
      "isUp": true,
      "lastCheck": 1757054439,
      "lastResultDuration": 225
    },
    "stats": {
      "allTime": {
        "total": 4223,
        "successful": 4222,
        "uptime": 99.98
      },
      "30d": {
        "total": 1212,
        "successful": 1212,
        "uptime": 100,
        "lastReset": 1755848047
      },
      "365d": {
        "total": 4223,
        "successful": 4222,
        "uptime": 99.98,
        "lastReset": 1753255731
      }
    }
  },
  {
    "config": {
      "address": "mail.agenturserver.de",
      "type": "host",
      "port": "995",
      "timeout": 5
    },
    "status": {
      "isUp": true,
      "lastCheck": 1757054440,
      "lastResultDuration": 222
    },
    "stats": {
      "allTime": {
        "total": 4223,
        "successful": 4219,
        "uptime": 99.91
      },
      "30d": {
        "total": 1212,
        "successful": 1210,
        "uptime": 99.83,
        "lastReset": 1755848047
      },
      "365d": {
        "total": 4223,
        "successful": 4219,
        "uptime": 99.91,
        "lastReset": 1753255731
      }
    }
  },
  {
    "config": {
      "address": "mail.agenturserver.de",
      "type": "host",
      "port": "465",
      "timeout": 5
    },
    "status": {
      "isUp": true,
      "lastCheck": 1757054440,
      "lastResultDuration": 113
    },
    "stats": {
      "allTime": {
        "total": 4223,
        "successful": 4218,
        "uptime": 99.88
      },
      "30d": {
        "total": 1212,
        "successful": 1211,
        "uptime": 99.92,
        "lastReset": 1755848047
      },
      "365d": {
        "total": 4223,
        "successful": 4218,
        "uptime": 99.88,
        "lastReset": 1753255731
      }
    }
  },
  {
    "config": {
      "address": "mail.agenturserver.de",
      "type": "host",
      "port": "587",
      "timeout": 5
    },
    "status": {
      "isUp": true,
      "lastCheck": 1757054440,
      "lastResultDuration": 227
    },
    "stats": {
      "allTime": {
        "total": 4223,
        "successful": 4222,
        "uptime": 99.98
      },
      "30d": {
        "total": 1212,
        "successful": 1212,
        "uptime": 100,
        "lastReset": 1755848048
      },
      "365d": {
        "total": 4223,
        "successful": 4222,
        "uptime": 99.98,
        "lastReset": 1753255731
      }
    }
  },
  {
    "config": {
      "address": "185.237.66.112",
      "type": "host",
      "port": "80",
      "timeout": 5
    },
    "status": {
      "isUp": true,
      "lastCheck": 1757054440,
      "lastResultDuration": 114
    },
    "stats": {
      "allTime": {
        "total": 4223,
        "successful": 4222,
        "uptime": 99.98
      },
      "30d": {
        "total": 1212,
        "successful": 1211,
        "uptime": 99.92,
        "lastReset": 1755848048
      },
      "365d": {
        "total": 4223,
        "successful": 4222,
        "uptime": 99.98,
        "lastReset": 1753255731
      }
    }
  },
  {
    "config": {
      "address": "157.97.45.248",
      "type": "host",
      "port": "80",
      "timeout": 5
    },
    "status": {
      "isUp": true,
      "lastCheck": 1757054440,
      "lastResultDuration": 113
    },
    "stats": {
      "allTime": {
        "total": 4223,
        "successful": 4222,
        "uptime": 99.98
      },
      "30d": {
        "total": 1212,
        "successful": 1211,
        "uptime": 99.92,
        "lastReset": 1755848048
      },
      "365d": {
        "total": 4223,
        "successful": 4222,
        "uptime": 99.98,
        "lastReset": 1753255731
      }
    }
  },
  {
    "config": {
      "address": "85.13.152.121",
      "type": "host",
      "port": "80",
      "timeout": 5
    },
    "status": {
      "isUp": true,
      "lastCheck": 1757054440,
      "lastResultDuration": 124
    },
    "stats": {
      "allTime": {
        "total": 4223,
        "successful": 4220,
        "uptime": 99.93
      },
      "30d": {
        "total": 1212,
        "successful": 1211,
        "uptime": 99.92,
        "lastReset": 1755848048
      },
      "365d": {
        "total": 4223,
        "successful": 4220,
        "uptime": 99.93,
        "lastReset": 1753255731
      }
    }
  },
  {
    "config": {
      "address": "https://login.pixelsaft.de",
      "type": "url",
      "port": null,
      "timeout": 5
    },
    "status": {
      "isUp": true,
      "lastCheck": 1757054441,
      "lastResultDuration": 757
    },
    "stats": {
      "allTime": {
        "total": 4223,
        "successful": 4211,
        "uptime": 99.72
      },
      "30d": {
        "total": 1212,
        "successful": 1206,
        "uptime": 99.5,
        "lastReset": 1755848049
      },
      "365d": {
        "total": 4223,
        "successful": 4211,
        "uptime": 99.72,
        "lastReset": 1753255731
      }
    }
  },
  {
    "config": {
      "address": "ns1.pixelsaft.de",
      "type": "host",
      "port": "53",
      "timeout": 5
    },
    "status": {
      "isUp": true,
      "lastCheck": 1757054441,
      "lastResultDuration": 238
    },
    "stats": {
      "allTime": {
        "total": 4223,
        "successful": 4222,
        "uptime": 99.98
      },
      "30d": {
        "total": 1212,
        "successful": 1212,
        "uptime": 100,
        "lastReset": 1755848050
      },
      "365d": {
        "total": 4223,
        "successful": 4222,
        "uptime": 99.98,
        "lastReset": 1753255731
      }
    }
  },
  {
    "config": {
      "address": "ns2.pixelsaft.de",
      "type": "host",
      "port": "53",
      "timeout": 5
    },
    "status": {
      "isUp": true,
      "lastCheck": 1757054441,
      "lastResultDuration": 229
    },
    "stats": {
      "allTime": {
        "total": 4223,
        "successful": 4221,
        "uptime": 99.95
      },
      "30d": {
        "total": 1212,
        "successful": 1212,
        "uptime": 100,
        "lastReset": 1755848051
      },
      "365d": {
        "total": 4223,
        "successful": 4221,
        "uptime": 99.95,
        "lastReset": 1753255731
      }
    }
  },
  {
    "config": {
      "address": "ns3.pixelsaft.de",
      "type": "host",
      "port": "53",
      "timeout": 5
    },
    "status": {
      "isUp": true,
      "lastCheck": 1757054442,
      "lastResultDuration": 207
    },
    "stats": {
      "allTime": {
        "total": 4223,
        "successful": 4219,
        "uptime": 99.91
      },
      "30d": {
        "total": 1212,
        "successful": 1212,
        "uptime": 100,
        "lastReset": 1755848052
      },
      "365d": {
        "total": 4223,
        "successful": 4219,
        "uptime": 99.91,
        "lastReset": 1753255731
      }
    }
  },
  {
    "config": {
      "address": "ns4.pixelsaft.de",
      "type": "host",
      "port": "53",
      "timeout": 5
    },
    "status": {
      "isUp": true,
      "lastCheck": 1757054442,
      "lastResultDuration": 108
    },
    "stats": {
      "allTime": {
        "total": 4223,
        "successful": 4221,
        "uptime": 99.95
      },
      "30d": {
        "total": 1212,
        "successful": 1211,
        "uptime": 99.92,
        "lastReset": 1755848052
      },
      "365d": {
        "total": 4223,
        "successful": 4221,
        "uptime": 99.95,
        "lastReset": 1753255731
      }
    }
  }
]